nupropagator/.Flux.py.swp
nupropagator/.NuPropagator.py.swo
nupropagator/.gitkeep
nupropagator/.test..swp
nupropagator/.test.py.swo
nupropagator/.test.swp
nupropagator/NuPropagator.py
nupropagator/NuPropogator.py
nupropagator/__about__.py
nupropagator/__init__.py
nupropagator/gen_utils.py
nupropagator/nugen.py
nupropagator/nuprop.py
nupropagator/Global/Global.py
nupropagator/Global/pdg_constants.py
nupropagator/Global/systemofunits.py
nupropagator/cross_section/.CT10nlo_2112_14_cc.dat.swp
nupropagator/cross_section/.CT10nlo_2112_14_nc.dat.swp
nupropagator/cross_section/.CT10nlo_2212_14_cc.dat.swp
nupropagator/cross_section/.CT10nlo_2212_14_nc.dat.swp
nupropagator/cross_section/.cross.py.swp
nupropagator/cross_section/.gitkeep
nupropagator/cross_section/CT10nlo_2112_12_cc.dat
nupropagator/cross_section/CT10nlo_2112_12_cc_max.dat
nupropagator/cross_section/CT10nlo_2112_12_nc.dat
nupropagator/cross_section/CT10nlo_2112_12_nc_max.dat
nupropagator/cross_section/CT10nlo_2112_14_cc.dat
nupropagator/cross_section/CT10nlo_2112_14_cc_max.dat
nupropagator/cross_section/CT10nlo_2112_14_nc.dat
nupropagator/cross_section/CT10nlo_2112_14_nc_max.dat
nupropagator/cross_section/CT10nlo_2112_16_cc.dat
nupropagator/cross_section/CT10nlo_2112_16_cc_max.dat
nupropagator/cross_section/CT10nlo_2112_16_nc.dat
nupropagator/cross_section/CT10nlo_2112_16_nc_max.dat
nupropagator/cross_section/CT10nlo_2212_12_cc.dat
nupropagator/cross_section/CT10nlo_2212_12_cc_max.dat
nupropagator/cross_section/CT10nlo_2212_12_nc.dat
nupropagator/cross_section/CT10nlo_2212_12_nc_max.dat
nupropagator/cross_section/CT10nlo_2212_14_cc.dat
nupropagator/cross_section/CT10nlo_2212_14_cc_max.dat
nupropagator/cross_section/CT10nlo_2212_14_nc.dat
nupropagator/cross_section/CT10nlo_2212_14_nc_max.dat
nupropagator/cross_section/CT10nlo_2212_16_cc.dat
nupropagator/cross_section/CT10nlo_2212_16_cc_max.dat
nupropagator/cross_section/CT10nlo_2212_16_nc.dat
nupropagator/cross_section/CT10nlo_2212_16_nc_max.dat
nupropagator-0.1.1.dist-info/METADATA
nupropagator-0.1.1.dist-info/WHEEL
nupropagator-0.1.1.dist-info/licenses/LICENSE.txt
nupropagator-0.1.1.dist-info/RECORD
